dektools-0.4.79.dist-info/METADATA
dektools-0.4.79.dist-info/WHEEL
dektools-0.4.79.dist-info/entry_points.txt
dektools/__init__.py
dektools/attr.py
dektools/cache/__init__.py
dektools/cache/base/__init__.py
dektools/cache/disk.py
dektools/cfg.py
dektools/click/__entry__.py
dektools/click/__init__.py
dektools/click/cfg.py
dektools/click/cmd.py
dektools/click/data.py
dektools/click/fetch.py
dektools/click/file.py
dektools/click/git.py
dektools/click/hash.py
dektools/click/linux/__entry__.py
dektools/click/linux/__init__.py
dektools/click/linux/ppa.py
dektools/click/net.py
dektools/click/pip.py
dektools/click/url.py
dektools/click/utils.py
dektools/click/version.py
dektools/click/win32/__entry__.py
dektools/click/win32/__init__.py
dektools/click/win32/wnd.py
dektools/cmd/__init__.py
dektools/cmd/git.py
dektools/collect.py
dektools/common.py
dektools/context/__init__.py
dektools/context/utils/__init__.py
dektools/context/utils/attr.py
dektools/context/utils/method.py
dektools/crypto/__init__.py
dektools/crypto/aes.py
dektools/crypto/rc4.py
dektools/derive.py
dektools/design/__init__.py
dektools/design/node/__init__.py
dektools/design/node/base/__init__.py
dektools/design/res/__init__.py
dektools/design/res/base/__init__.py
dektools/design/set/__init__.py
dektools/design/set/base/__init__.py
dektools/design/utils.py
dektools/dict/__init__.py
dektools/dict/chain.py
dektools/dict/cmp.py
dektools/dict/collections/__init__.py
dektools/dict/collections/orderedset.py
dektools/dict/configurable.py
dektools/dict/flat.py
dektools/dict/simple.py
dektools/dispatcher.py
dektools/download.py
dektools/encode/__init__.py
dektools/encode/b62.py
dektools/env.py
dektools/escape/__init__.py
dektools/escape/str.py
dektools/expression.py
dektools/expression_async.py
dektools/ext/__init__.py
dektools/ext/audio.py
dektools/ext/font.py
dektools/ext/image.py
dektools/ext/video.py
dektools/extraction/__init__.py
dektools/extraction/base/__init__.py
dektools/extraction/base/storage.py
dektools/extraction/base/value.py
dektools/extraction/base/variables.py
dektools/extraction/filter/__init__.py
dektools-0.4.79.dist-info/RECORD
