Metadata-Version: 2.1
Name: dektools
Version: 0.4.79
Author-Email: sanzenwin <sanzenwin@gmail.com>
License: MIT
Requires-Python: >=3.7
Requires-Dist: typer<=0.16.0
Requires-Dist: importlib_metadata<=8.7.0; python_version < "3.10"
Provides-Extra: date
Requires-Dist: tzdata; extra == "date"
Requires-Dist: backports.zoneinfo; python_version < "3.9" and extra == "date"
Provides-Extra: jsonpath
Requires-Dist: jsonpath-ng<=1.6.1; extra == "jsonpath"
Provides-Extra: ignore
Requires-Dist: gitignore-parser<=0.1.11; extra == "ignore"
Provides-Extra: yaml
Requires-Dist: pyyaml<=6.0.1; extra == "yaml"
Requires-Dist: yamlloader<=1.3.2; extra == "yaml"
Provides-Extra: uid
Requires-Dist: snowflake-id<=0.0.5; extra == "uid"
Provides-Extra: encode
Requires-Dist: pybase62<=1.0.0; extra == "encode"
Provides-Extra: crypto
Requires-Dist: pycryptodome<=3.18.0; extra == "crypto"
Provides-Extra: exec
Requires-Dist: RestrictedPython<=8.0; python_version >= "3.9" and python_version < "3.14" and extra == "exec"
Provides-Extra: dyna
Requires-Dist: dynaconf<=3.2.11; extra == "dyna"
Provides-Extra: sync
Requires-Dist: asgiref<4; extra == "sync"
Provides-Extra: async
Requires-Dist: async-eval<=0.3.1; extra == "async"
Provides-Extra: graph
Requires-Dist: networkx<=3.3; extra == "graph"
Requires-Dist: pydot<=3.0.1; extra == "graph"
Provides-Extra: win32
Requires-Dist: pypiwin32<300,>=219; sys_platform == "win32" and extra == "win32"
Requires-Dist: pywin32<400,>=300; sys_platform == "win32" and extra == "win32"
Provides-Extra: np
Requires-Dist: numpy<=2.2.1; extra == "np"
Provides-Extra: cv
Requires-Dist: dektools[np]; extra == "cv"
Requires-Dist: opencv-python-headless<=4.10.0.84; extra == "cv"
Provides-Extra: pil
Requires-Dist: pillow<=10.3.0; extra == "pil"
Provides-Extra: version
Requires-Dist: semver<=3.0.2; extra == "version"
Provides-Extra: js
Requires-Dist: quickjs<=1.19.4; extra == "js"
Provides-Extra: fetch
Requires-Dist: urllib3<=1.26.15; extra == "fetch"
Provides-Extra: tab
Requires-Dist: tabulate<=0.9.0; extra == "tab"
Provides-Extra: ps
Requires-Dist: psutil<=7.0.0; extra == "ps"
Requires-Dist: dektools[tab]; extra == "ps"
Provides-Extra: mem
Requires-Dist: pympler<=1.1; extra == "mem"
Provides-Extra: all
Requires-Dist: dektools[async,crypto,date,dyna,encode,exec,fetch,graph,ignore,js,jsonpath,sync,uid,version,yaml]; extra == "all"
